{
    "name": "Firebase",
    "id": "firebase-cli",
    "version": "1.1.7",
    "description": "The Firebase CLI (GitHub) provides a variety of tools for managing, viewing, and deploying to Firebase projects.",
    "documentationURL": "http://github.com/devcontainers-contrib/features/tree/main/src/firebase-cli",
    "installAfter": [
        "ghcr.io/devcontainers/features/python:latest"
    ],
    "options": {
        "version": {
            "type": "boolean",
            "proposals": [
                "latest"
            ],
            "default": "latest",
            "description": "Select the version of Firebase to install."
        }
    }
}