{
    "id": "upx",
    "version": "1.0.14",
    "name": "UPX (via Github Releases)",
    "documentationURL": "http://github.com/devcontainers-contrib/features/tree/main/src/upx",
    "description": "UPX is a free, secure, portable, extendable, high-performance executable packer for several executable formats.",
    "options": {
        "version": {
            "default": "latest",
            "description": "Select the version to install.",
            "proposals": [
                "latest"
            ],
            "type": "string"
        }
    },
    "installsAfter": [
        "ghcr.io/devcontainers-contrib/features/gh-release"
    ]
}